pyserialgateway/INSERTCSVNAMEHERE.csv
pyserialgateway/PYGatewayListener.py
pyserialgateway/config_PYproperties.py
pyserialgateway/hardware_reset.py
pyserialgateway/hardware_reset_type2.py
pyserialgateway/required-dbklgw.zip
pyserialgateway/GPSlog/README.md
pyserialgateway/errorlog/README.md
pyserialgateway/log/README.md
pyserialgateway-1.3.19.dist-info/DESCRIPTION.rst
pyserialgateway-1.3.19.dist-info/METADATA
pyserialgateway-1.3.19.dist-info/RECORD
pyserialgateway-1.3.19.dist-info/WHEEL
pyserialgateway-1.3.19.dist-info/metadata.json
pyserialgateway-1.3.19.dist-info/top_level.txt
