Metadata-Version: 2.0
Name: pyserialgateway
Version: 1.3.19
Summary: Classes dedicated for multi-functioned processes which includes DB, mapping, data and connection capabilities.
Home-page: https://github.com/joeyee-senatraffic/pyserialgateway.git
Author: ljyee
Author-email: joeyee@senatraffic.com.my
License: MIT
Platform: UNKNOWN
Requires-Python: >=3.5
Requires-Dist: psutil (>=5.6.7)
Requires-Dist: psycopg2 (>=2.8.5)
Requires-Dist: pykml (>=0.2.0)
Requires-Dist: pyserial (>=3.5)
